Metadata-Version: 2.1
Name: sportsfeatures
Version: 0.0.120
Summary: A library for processing sports features over a dataframe containing sports data.
Home-page: https://github.com/8W9aG/sports-features
Author: Will Sackfield
Author-email: will.sackfield@gmail.com
License: MIT
Keywords: features,sports
Classifier: License :: OSI Approved :: MIT License
Classifier: Programming Language :: Python :: 3
License-File: LICENSE
Requires-Dist: openskill>=6.0.2
Requires-Dist: pandas>=2.2.3
Requires-Dist: feature-engine>=1.8.3
Requires-Dist: tqdm>=4.67.1
Requires-Dist: scikit-learn>=1.5.2
Requires-Dist: geopy>=2.4.1
Requires-Dist: numpy>=1.26.4
Requires-Dist: pytest-is-running>=1.5.1
Requires-Dist: joblib>=1.4.2
Requires-Dist: timeseriesfeatures>=0.0.17
Requires-Dist: textfeats>=0.1.4
Requires-Dist: scipy>=1.15.2
Requires-Dist: imagefeatures>=0.0.2
Requires-Dist: requests-cache>=1.2.1
